smokesign/__init__.py
smokesign-0.0.1.dist-info/METADATA
smokesign-0.0.1.dist-info/WHEEL
smokesign-0.0.1.dist-info/RECORD
