Metadata-Version: 2.1
Name: smokesign
Version: 0.0.1
Summary: A library intended to establish WebRTC communication between peers without relying on a central handshake server by using Autonomi Scratchpads for the handshake.
License: MIT
Author: riddim
Requires-Python: >=3.10,<4.0
Classifier: License :: OSI Approved :: MIT License
Classifier: Programming Language :: Python :: 3
Classifier: Programming Language :: Python :: 3.10
Classifier: Programming Language :: Python :: 3.11
Classifier: Programming Language :: Python :: 3.12
